molliesim/__init__.py
molliesim/router.py
molliesim/server.py
molliesim/storage.py
molliesim/api/__init__.py
molliesim/api/utils.py
molliesim/api/payments/__init__.py
molliesim/api/payments/endpoints.py
molliesim/api/payments/models.py
molliesim-0.0.1.dist-info/WHEEL
molliesim-0.0.1.dist-info/METADATA
molliesim-0.0.1.dist-info/RECORD
