Metadata-Version: 2.1
Name: molliesim
Version: 0.0.1
Summary: Simulator of the Mollie API for testing purposes.
Requires-Python: >=3.5
Classifier: Development Status :: 3 - Alpha
Classifier: License :: OSI Approved :: BSD License
Classifier: Programming Language :: Python :: 3
Classifier: Programming Language :: Python :: 3.5
Requires-Dist: pydantic ~= 1.9
